{
   "entries":
   [
      {
         "id" : "tenshi_trinket_peachbox",
         "buffs" : 
         [
            "tenshi_peachbox_stresshealr",
			"tenshi_peachbox_healr"
         ],
         "hero_class_requirements":
         [
            "tenshi"
         ],
         "rarity" : "common",
         "price" : 7500,
         "limit" : 0,
         "origin_dungeon" : ""
      },
	  {
         "id" : "tenshi_trinket_token",
         "buffs" : 
         [
			"tenshi_token_move",
			"tenshi_token_stunr"
         ],
         "hero_class_requirements":
         [
            "tenshi"
         ],
         "rarity" : "uncommon",
         "price" : 10000,
         "limit" : 0,
         "origin_dungeon" : ""
      },
	  {
         "id" : "tenshi_trinket_mallet",
         "buffs" : 
         [
			"tenshi_mallet_acc",
			"tenshi_mallet_crit",
			"tenshi_mallet_critr",
			"tenshi_mallet_fuckyourtruncation_Desk",
			"tenshi_mallet_DMGL-10",
			"tenshi_mallet_DMGH-10"
         ],
         "hero_class_requirements":
         [
            "tenshi"
         ],
         "rarity" : "rare",
         "price" : 15000,
         "limit" : 0,
         "origin_dungeon" : ""
      },
	  {
         "id" : "tenshi_trinket_shion",
         "buffs" : 
         [
			"tenshi_shion_eat",
			"tenshi_shion_stressinf",
			"tenshi_shion_stress"
         ],
         "hero_class_requirements":
         [
            "tenshi"
         ],
         "rarity" : "very_rare",
         "price" : 25000,
         "limit" : 1,
         "origin_dungeon" : ""
      },
	  {
         "id" : "tenshi_trinket_hakureikeystone",
         "buffs" : 
         [
			"tenshi_hakurei_mhp",
			"tenshi_harurei_Desk",
			"tenshi_hakurei_bleed",
			"tenshi_hakurei_blight"
         ],
         "hero_class_requirements":
         [
            "tenshi"
         ],
         "rarity" : "very_rare",
         "price" : 25000,
         "limit" : 1,
         "origin_dungeon" : "",
		 "riposte_skill_additional_effects":
         [
			 "FUMO BREAK"
         ] 
      },
	  {
         "id" : "tenshi_trinket_scarf",
         "buffs" : 
         [
			"tenshi_scarf_riposte_dmgl",
			"tenshi_scarf_riposte_dmgh",
			"tenshi_scarf_move_Desk",
			"tenshi_scarf_swr_friendly_Desk",
			"tenshi_scarf_swr_party_Desk",
			"tenshi_scarf_swr_tenshi_Desk",
			"tenshi_scarf_swr_magician_Desk",
			"tenshi_scarf_swr_maid_Desk",
			"tenshi_scarf_swr_miko_Desk",
			"tenshi_scarf_swr_disclaimer_Desk",
			"tenshi_scarf_cleaner_Desk"
         ],
         "hero_class_requirements":
         [
            "tenshi"
         ],
		 "set_id" : "tenshi_sunward_fluff_set",
         "rarity" : "sakura",
         "price" : 30000,
         "limit" : 1,
         "origin_dungeon" : "",
		 "ranged_attack_skill_additional_effects":
         [
			 "Fumo Swagger"
         ],
		 "friendly_skill_additional_effects":
		 [
			 "Scarlet Weather Rhapsody 1",
			 "Scarlet Weather Rhapsody 2"
		 ]
      }
	]
}